funclift/__init__.py
funclift/applicative.py
funclift/bifunctor.py
funclift/category.py
funclift/exceptions.py
funclift/foldable.py
funclift/fp/__init__.py
funclift/fp/curry.py
funclift/fp/monad_runner.py
funclift/free_applicative.py
funclift/free_monad.py
funclift/functor.py
funclift/monad.py
funclift/monoid.py
funclift/profunctor.py
funclift/py.typed
funclift/semigroup.py
funclift/semigroupal.py
funclift/traverable.py
funclift/types/__init__.py
funclift/types/aio.py
funclift/types/clist.py
funclift/types/compose.py
funclift/types/costar.py
funclift/types/either.py
funclift/types/future.py
funclift/types/id.py
funclift/types/io.py
funclift/types/option.py
funclift/types/optiont.py
funclift/types/predicate.py
funclift/types/reader.py
funclift/types/result.py
funclift/types/star.py
funclift/types/state.py
funclift/types/tree.py
funclift/types/validated.py
funclift/types/writer.py
funclift-0.2.0.dist-info/LICENSE
funclift-0.2.0.dist-info/METADATA
funclift-0.2.0.dist-info/WHEEL
funclift-0.2.0.dist-info/RECORD
