Metadata-Version: 2.1
Name: funclift
Version: 0.2.0
Summary: 
Author: Essentier
Author-email: support@essentier.com
Requires-Python: >=3.11,<4.0
Classifier: Programming Language :: Python :: 3
Classifier: Programming Language :: Python :: 3.11
Classifier: Programming Language :: Python :: 3.12
